beautypix/__init__.py
beautypix/bpix.py
beautypix-1.0.0.dist-info/METADATA
beautypix-1.0.0.dist-info/WHEEL
beautypix-1.0.0.dist-info/top_level.txt
beautypix-1.0.0.dist-info/RECORD
