Metadata-Version: 2.1
Name: beautypix
Version: 1.0.0
Summary: BeautyPix is a versatile Python tool designed for capturing and managing screenshots of specified domains. It efficiently captures screenshots. Ideal for web developers, testers, and digital archivists, BeautyPix simplifies the process of monitoring and documenting web content
Home-page: https://github.com/MrHorbio/bpix/blob/main/bpix_package/README.md
Author: Ankush Kumar Rajput (Mr.Horbio)
License: MIT
Classifier: Programming Language :: Python :: 3
Classifier: License :: OSI Approved :: MIT License
Classifier: Operating System :: OS Independent
Requires-Python: >=3.6
Requires-Dist: selenium
Requires-Dist: requests
Requires-Dist: sockets
